[{"n":"AGINCARE HERITAGE LIMITED","num":"10618905","sic":"91020","y":"2017","t":"PORTLAND","r":"DORSET","pc":"DT5 1BB","ac":"A"},{"n":"AQUARIUM EXPLORIS LIMITED","num":"NI637397","sic":"91030","y":"2016","t":"BELFAST","r":"ANTRIM","pc":"BT14 6ST","ac":"U"},{"n":"ARCADE ARCHIVE LTD","num":"14345385","sic":"91020","y":"2022","t":"STROUD","r":"","pc":"GL6 8NS","ac":"U"},{"n":"ARCHAEOLOGICAL SOLUTIONS LIMITED","num":"04702122","sic":"91012","y":"2003","t":"STOKE-ON-TRENT","r":"STAFFORDSHIRE","pc":"ST1 5BD","ac":"S"},{"n":"ARCHIVE DOCUMENT DATA STORAGE LIMITED","num":"05217145","sic":"91012","y":"2004","t":"STANFORD-LE-HOPE","r":"ESSEX","pc":"SS17 9ER","ac":"U"},{"n":"BAC TRADING LIMITED","num":"05078738","sic":"91020","y":"2004","t":"BRISTOL","r":"","pc":"BS34 5BZ","ac":"S"},{"n":"BAMBURGH CASTLE VIEWING LIMITED","num":"07570393","sic":"91030","y":"2011","t":"LEEDS","r":"","pc":"LS1 4AP","ac":"F"},{"n":"BEAMISH MUSEUM TRADING LIMITED","num":"06525165","sic":"91020","y":"2008","t":"STANLEY","r":"","pc":"DH9 0RG","ac":"S"},{"n":"BENBURB PRIORY LTD","num":"NI671241","sic":"91020","y":"2020","t":"DUNGANNON","r":"","pc":"BT71 7JZ","ac":"A"},{"n":"BLENHEIM VISITORS LIMITED","num":"05957291","sic":"91030","y":"2006","t":"WOODSTOCK","r":"OXFORDSHIRE","pc":"OX20 1PP","ac":"F"},{"n":"BORDERS SPORT AND LEISURE ENTERPRISES LIMITED","num":"SC244374","sic":"91011","y":"2003","t":"MELROSE","r":"","pc":"TD6 0SA","ac":"S"},{"n":"BRACEBRIDGE HOLDINGS LIMITED","num":"03034038","sic":"91020","y":"1995","t":"SOLIHULL","r":"WEST MIDLANDS","pc":"B91 2TH","ac":"G"},{"n":"BRISTOL, CLIFTON AND WEST OF ENGLAND ZOOLOGICAL SOCIETY LIMITED","num":"05154176","sic":"91040","y":"2004","t":"BRISTOL","r":"","pc":"BS10 7TW","ac":"G"},{"n":"BUCKENHAM AVIATION CENTRE LIMITED","num":"08689952","sic":"91030","y":"2013","t":"BUXHALL","r":"SUFFOLK","pc":"IP14 3DY","ac":"U"},{"n":"BUGTOPIA (HORNSEA) LTD","num":"10215952","sic":"91040","y":"2016","t":"TUGBY","r":"LEICESTERSHIRE","pc":"LE7 9WE","ac":"U"},{"n":"CARTHUSIA LIMITED","num":"07612570","sic":"91030","y":"2011","t":"LONDON","r":"","pc":"EC1M 6AN","ac":"S"},{"n":"CHILHAM CASTLE ESTATE LIMITED","num":"13992837","sic":"91030","y":"2022","t":"CANTERBURY","r":"","pc":"CT4 8DB","ac":"U"},{"n":"CHURCHES CONSERVATION TRUST ENTERPRISES LIMITED","num":"08125965","sic":"91030","y":"2012","t":"NORTHAMPTON","r":"","pc":"NN1 1FH","ac":"S"},{"n":"CLIFTON HOUSE CENTRE LIMITED","num":"NI605357","sic":"91030","y":"2010","t":"BELFAST","r":"CO. ANTRIM","pc":"BT15 1EQ","ac":"S"},{"n":"CLYDE MARITIME CENTRE LIMITED","num":"SC141269","sic":"91030","y":"1992","t":"GLASGOW","r":"","pc":"G3 8RS","ac":"A"},{"n":"COLNAGHI LIBRARY AND ARCHIVES LTD","num":"12101271","sic":"91011","y":"2019","t":"LONDON","r":"","pc":"SW1Y 6AL","ac":"S"},{"n":"COMLONGON ESTATE LIMITED","num":"SC384422","sic":"91030","y":"2010","t":"ANNAN","r":"DUMFRIESSHIRE","pc":"DG12 5LL","ac":"A"},{"n":"CONTINUUM (LOCH NESS) LIMITED","num":"11413196","sic":"91030","y":"2018","t":"YORK","r":"NORTH YORKSHIRE","pc":"YO10 4UX","ac":"S"},{"n":"COTSWOLDS AUTOMOTIVE DEVELOPMENT COMPANY LIMITED","num":"14332898","sic":"91020","y":"2022","t":"LONDON","r":"","pc":"SW1H 0DB","ac":"S"},{"n":"CRESWELL TRADING COMPANY LIMITED","num":"02467865","sic":"91030","y":"1990","t":"WORKSOP","r":"NOTTS","pc":"S80 3LH","ac":"S"},{"n":"DERBY MUSEUMS ENTERPRISES LIMITED","num":"08119695","sic":"91020","y":"2012","t":"DERBY","r":"","pc":"DE1 1BS","ac":"S"},{"n":"DESIGN DUNDEE ENTERPRISES LIMITED","num":"SC531564","sic":"91020","y":"2016","t":"DUNDEE","r":"","pc":"DD1 4BJ","ac":"S"},{"n":"DGI LIBRARY LIMITED","num":"04617391","sic":"91011","y":"2002","t":"LONDON","r":"","pc":"N1C 4DJ","ac":"F"},{"n":"DURHAM CATHEDRAL OPEN TREASURE LIMITED","num":"08009824","sic":"91020","y":"2012","t":"DURHAM","r":"UK","pc":"DH1 3EH","ac":"S"},{"n":"EAST LANCASHIRE RAILWAY LIMITED","num":"12381729","sic":"91030","y":"2019","t":"BURY","r":"LANCASHIRE","pc":"BL9 0EY","ac":"S"},{"n":"ELEMENTAL TEMPLE LTD","num":"11840510","sic":"91012","y":"2019","t":"ELY","r":"","pc":"CB7 5RG","ac":"U"},{"n":"ESSEX WATERWAYS LIMITED","num":"05545459","sic":"91030","y":"2005","t":"CHELMSFORD","r":"","pc":"CM3 4BS","ac":"S"},{"n":"FIFE CULTURAL SERVICES TRADING LIMITED","num":"SC433176","sic":"91011","y":"2012","t":"KIRKCALDY","r":"FIFE","pc":"KY2 6NA","ac":"S"},{"n":"FIVE SISTERS ZOO LIMITED","num":"SC377723","sic":"91040","y":"2010","t":"WEST CALDER","r":"WEST LOTHIAN","pc":"EH55 8PT","ac":"U"},{"n":"FONMON CASTLE LIMITED","num":"11603833","sic":"91030","y":"2018","t":"ALCESTER","r":"","pc":"B49 6NQ","ac":"S"},{"n":"FRAMELESS CREATIVE LIMITED","num":"13828120","sic":"91020","y":"2022","t":"LONDON","r":"","pc":"W1H 7EJ","ac":"G"},{"n":"FRAMELESS LONDON LTD","num":"13515416","sic":"91020","y":"2021","t":"LONDON","r":"","pc":"W1H 7EJ","ac":"F"},{"n":"GLASGOW SCIENCE CENTRE (TRADING) LIMITED","num":"SC210177","sic":"91020","y":"2000","t":"LANARKSHIRE","r":"","pc":"G51 1EA","ac":"F"},{"n":"GOLF MUSEUM SERVICES LIMITED","num":"SC488042","sic":"91020","y":"2014","t":"ST ANDREWS","r":"FIFE","pc":"KY16 9JA","ac":"S"},{"n":"GREENWICH TRADING COMPANY LIMITED","num":"03568453","sic":"91030","y":"1998","t":"LONDON","r":"","pc":"SE10 9LW","ac":"S"},{"n":"HELIGAN GARDENS LIMITED","num":"02557448","sic":"91030","y":"1990","t":"ST AUSTELL","r":"CORNWALL","pc":"PL26 6EN","ac":"F"},{"n":"HERITAGE PROJECTS (OXFORD CASTLE) LTD","num":"05763243","sic":"91030","y":"2006","t":"NORTH YORKSHIRE","r":"","pc":"YO10 4UX","ac":"S"},{"n":"HERITAGE PROJECTS (YORK) LIMITED","num":"07618476","sic":"91030","y":"2011","t":"YORK","r":"","pc":"YO10 4UX","ac":"S"},{"n":"HOPETOUN HOUSE LIMITED","num":"SC135734","sic":"91030","y":"1991","t":"WEST LOTHIAN","r":"","pc":"EH30 9SL","ac":"S"},{"n":"HORNIMAN MUSEUM ENTERPRISES LIMITED","num":"05210248","sic":"91020","y":"2004","t":"","r":"","pc":"SE23 3PQ","ac":"S"},{"n":"ISLAND AMAZON ADVENTURE LIMITED","num":"02693563","sic":"91040","y":"1992","t":"BERKSHIRE","r":"","pc":"SL6 4AA","ac":"U"},{"n":"ITN ARCHIVE LIMITED","num":"03807324","sic":"91011","y":"1999","t":"","r":"","pc":"WC1X 8XZ","ac":"U"},{"n":"JANE AUSTEN LTD","num":"03656831","sic":"91020","y":"1998","t":"BATH","r":"","pc":"BA1 2NT","ac":"U"},{"n":"JJJ & A ENTERPRISES LIMITED","num":"04596335","sic":"9112","y":"2002","t":"WEST MALLING","r":"KENT","pc":"ME19 4HE","ac":"F"},{"n":"KILMARTIN HOUSE TRADING CO LTD.","num":"SC166302","sic":"91020","y":"1996","t":"LOCHGILPHEAD","r":"ARGYLL","pc":"PA31 8RQ","ac":"S"},{"n":"KINGSTON MAURWARD ENTERPRISES LIMITED","num":"05472379","sic":"91030","y":"2005","t":"DORSET","r":"","pc":"DT2 8PY","ac":"S"},{"n":"LAKELAND MOTOR MUSEUM LIMITED","num":"05957608","sic":"91020","y":"2006","t":"BOWNESS ON WINDERMERE","r":"CUMBRIA","pc":"LA23 3HE","ac":"A"},{"n":"LEBRECHT LIMITED","num":"06937508","sic":"91011","y":"2009","t":"LONDON","r":"","pc":"W2 4PH","ac":"A"},{"n":"LIVINGSTONE LEISURE LIMITED","num":"07560247","sic":"91040","y":"2011","t":"SHERBORNE","r":"DORSET","pc":"DT9 3NX","ac":"U"},{"n":"LONDON TRANSPORT MUSEUM (TRADING) LIMITED","num":"06527755","sic":"91020","y":"2008","t":"LONDON","r":"","pc":"E20 1JN","ac":"S"},{"n":"LONDON TRANSPORT MUSEUM LIMITED","num":"06495761","sic":"91020","y":"2008","t":"LONDON","r":"","pc":"E20 1JN","ac":"G"},{"n":"MABLETHORPE SEAL SANCTUARY LIMITED","num":"07569897","sic":"91040","y":"2011","t":"MABLETHORPE","r":"","pc":"LN12 1QG","ac":"U"},{"n":"MANCHESTER ART GALLERY TRADING COMPANY LIMITED","num":"04465391","sic":"91020","y":"2002","t":"MANCHESTER","r":"","pc":"M2 3JL","ac":"S"},{"n":"MERLIN ENTERTAINMENTS (DUNGEONS) LIMITED","num":"03671067","sic":"91030","y":"1998","t":"LONDON","r":"","pc":"SE1 9AX","ac":"A"},{"n":"MERLIN ENTERTAINMENTS GROUP OPERATIONS LIMITED","num":"03671093","sic":"91030","y":"1998","t":"LONDON","r":"","pc":"SE1 9AX","ac":"A"},{"n":"MILLER LEISURE LIMITED","num":"03978774","sic":"91040","y":"2000","t":"LEIGH-ON-SEA","r":"ESSEX","pc":"SS9 2AD","ac":"S"},{"n":"MOCO MUSEUM LONDON LTD","num":"14082175","sic":"91020","y":"2022","t":"LONDON","r":"","pc":"W1H 7AL","ac":"S"},{"n":"MONKEY WORLD LIMITED","num":"02548930","sic":"91040","y":"1990","t":"DORSET","r":"","pc":"BH20 6HH","ac":"S"},{"n":"MUSEUM OF BRANDS TRADING LIMITED","num":"09920989","sic":"91020","y":"2015","t":"LONDON","r":"","pc":"W11 1QT","ac":"S"},{"n":"MUSEUM OF FREE DERRY LTD","num":"NI630581","sic":"91020","y":"2015","t":"DERRY","r":"","pc":"BT48 9DR","ac":"S"},{"n":"NATIONAL FOOTBALL MUSEUM AT URBIS (TRADING) LIMITED","num":"07539263","sic":"91020","y":"2011","t":"MANCHESTER","r":"GREATER MANCHESTER","pc":"M4 3BG","ac":"F"},{"n":"NATIONAL JUSTICE MUSEUM TRADING LIMITED","num":"03476430","sic":"91020","y":"1997","t":"NOTTINGHAM","r":"NOTTINGHAMSHIRE","pc":"NG1 1HN","ac":"S"},{"n":"NATIONAL MOTOR MUSEUM TRADING LIMITED","num":"02679294","sic":"91020","y":"1992","t":"BROCKENHURST","r":"HAMPSHIRE","pc":"SO42 7ZN","ac":"S"},{"n":"NATIONAL PORTRAIT GALLERY COMPANY LIMITED","num":"06015724","sic":"91020","y":"2006","t":"LONDON","r":"","pc":"WC2H 0HE","ac":"S"},{"n":"NAVY WINGS HERITAGE FLIGHT LIMITED","num":"07052646","sic":"91030","y":"2009","t":"ILCHESTER","r":"SOMERSET","pc":"BA22 8HT","ac":"S"},{"n":"NDA ARCHIVES LIMITED","num":"09109416","sic":"91012","y":"2014","t":"MOOR ROW","r":"","pc":"CA24 3HU","ac":"A"},{"n":"NMA OPERATIONS LIMITED","num":"02972338","sic":"91040","y":"1994","t":"PLYMOUTH","r":"DEVON","pc":"PL4 0LF","ac":"F"},{"n":"ORCM LTD","num":"13283041","sic":"91040","y":"2021","t":"CANTERBURY","r":"","pc":"CT2 7EX","ac":"U"},{"n":"PALACE ENTERPRISES (WELLS) LIMITED","num":"03013064","sic":"91030","y":"1995","t":"WELLS","r":"SOMERSET","pc":"BA5 2PD","ac":"S"},{"n":"PIECE HALL ENTERPRISES LIMITED","num":"09761837","sic":"91030","y":"2015","t":"HALIFAX","r":"WEST YORKSHIRE","pc":"HX1 1RE","ac":"S"},{"n":"PORTSMOUTH HISTORIC DOCKYARD OPERATIONS LIMITED","num":"12799836","sic":"91030","y":"2020","t":"PORTSMOUTH","r":"HAMPSHIRE","pc":"PO1 3NH","ac":"S"},{"n":"POSTAL HERITAGE SERVICES LIMITED","num":"05079374","sic":"91012","y":"2004","t":"LONDON","r":"","pc":"WC1X 0DA","ac":"S"},{"n":"PRENAX LIMITED","num":"03966286","sic":"91011","y":"2000","t":"YEOVIL","r":"SOMERSET","pc":"BA20 2HL","ac":"F"},{"n":"R3STORE STUDIOS LIMITED","num":"10212733","sic":"91012","y":"2016","t":"ASHFORD","r":"","pc":"TW15 1BL","ac":"S"},{"n":"RE-FORM HERITAGE TRADING LIMITED","num":"07169150","sic":"91030","y":"2010","t":"STOKE-ON-TRENT","r":"","pc":"ST6 3PE","ac":"S"},{"n":"RM EXPERIENCE LIMITED","num":"10953110","sic":"91030","y":"2017","t":"PONTYCLUN","r":"","pc":"CF72 8YT","ac":"A"},{"n":"SEVEN STORIES TRADING LIMITED","num":"04177830","sic":"91020","y":"2001","t":"NEWCASTLE UPON TYNE","r":"TYNE & WEAR","pc":"NE1 2PQ","ac":"S"},{"n":"SOANE MUSEUM ENTERPRISES LIMITED","num":"08171280","sic":"91020","y":"2012","t":"LONDON","r":"","pc":"WC2A 3BP","ac":"S"},{"n":"SOUTH WEST HERITAGE TRUST TRADING LIMITED","num":"09222720","sic":"91011","y":"2014","t":"TAUNTON","r":"","pc":"TA2 6SF","ac":"S"},{"n":"SOUTHBANK CENTRE ENTERPRISES LIMITED","num":"06158790","sic":"91030","y":"2007","t":"LONDON","r":"","pc":"SE1 8XX","ac":"F"},{"n":"ST. ANDREWS AQUARIUM LIMITED","num":"SC198797","sic":"91020","y":"1999","t":"ST. ANDREWS","r":"","pc":"KY16 0BQ","ac":"U"},{"n":"STOWE HOUSE ENTERPRISES LIMITED","num":"03634573","sic":"91030","y":"1998","t":"BUCKINGHAMSHIRE","r":"","pc":"MK18 5EH","ac":"S"},{"n":"SUPASTORAGE LIMITED","num":"06406369","sic":"91012","y":"2007","t":"LONDON","r":"","pc":"SW19 2RR","ac":"S"},{"n":"SUSSEX PAST TRADING LTD.","num":"03355746","sic":"91030","y":"1997","t":"LEWES","r":"EAST SUSSEX","pc":"BN7 1YE","ac":"S"},{"n":"TAP TRADING LIMITED","num":"08148123","sic":"91030","y":"2012","t":"BISHOP AUCKLAND","r":"","pc":"DL14 7JF","ac":"S"},{"n":"THE CHILDREN`S DISCOVERY ZONE LIMITED","num":"05357860","sic":"91020","y":"2005","t":"LIVERPOOL","r":"MERSEYSIDE","pc":"L13 1EH","ac":"U"},{"n":"THE GLASS ONION EXHIBITIONS LIMITED","num":"09901059","sic":"91020","y":"2015","t":"ST HELENS","r":"MERSEYSIDE","pc":"WA10 1DB","ac":"U"},{"n":"THE HILL COMPANY LIMITED","num":"04959684","sic":"91012","y":"2003","t":"WEST THURROCK","r":"ESSEX","pc":"RM20 3LB","ac":"F"},{"n":"THE LONDON TUNNELS LTD","num":"13160590","sic":"91030","y":"2021","t":"CHICHESTER","r":"WEST SUSSEX","pc":"PO19 8SE","ac":"F"},{"n":"THE MONASTERY MANCHESTER LIMITED","num":"03481132","sic":"91030","y":"1997","t":"MANCHESTER","r":"GREATER MANCHESTER","pc":"M12 5WF","ac":"S"},{"n":"THE REAL LIVE LEISURE COMPANY LIMITED","num":"03446630","sic":"91040","y":"1997","t":"BOURNEMOUTH","r":"","pc":"BH2 5AA","ac":"F"},{"n":"THE ROALD DAHL CENTRE (TRADING) LIMITED","num":"04854808","sic":"91012","y":"2003","t":"BUCKINGHAMSHIRE","r":"","pc":"HP16 0AL","ac":"S"},{"n":"TITANIC BELFAST NOMADIC COMPANY LIMITED","num":"NI629209","sic":"91030","y":"2015","t":"BELFAST","r":"","pc":"BT2 7FW","ac":"S"},{"n":"TRENTHAM LEISURE LTD.","num":"03246990","sic":"91030","y":"1996","t":"TRENTHAM","r":"STAFFORDSHIRE","pc":"ST4 8JG","ac":"S"},{"n":"TRENTHAM MONKEY FOREST LIMITED","num":"05153758","sic":"91040","y":"2004","t":"STOKE-ON-TRENT","r":"","pc":"ST4 8AY","ac":"S"},{"n":"UV&S LTD","num":"08485503","sic":"91011","y":"2013","t":"ASHFORD","r":"MIDDLESEX","pc":"TW15 1BL","ac":"G"},{"n":"V&A MUSEUM EVENTS LIMITED","num":"09337645","sic":"91020","y":"2014","t":"LONDON","r":"","pc":"SW7 2RL","ac":"U"},{"n":"WEARDALE RAILWAY LIMITED","num":"12392050","sic":"91030","y":"2020","t":"BISHOP AUCKLAND","r":"","pc":"DL14 7JF","ac":"S"},{"n":"WENTWORTH WOODHOUSE TRADING LIMITED","num":"10891000","sic":"91030","y":"2017","t":"ROTHERHAM","r":"SOUTH YORKSHIRE","pc":"S62 7TQ","ac":"S"},{"n":"WILD LIFE GROUP LIMITED","num":"06531168","sic":"91040","y":"2008","t":"DONCASTER","r":"","pc":"DN3 3NH","ac":"F"},{"n":"WILD ZOOLOGICAL PARK LTD","num":"10295020","sic":"91040","y":"2016","t":"BOBBINGTON","r":"WEST MIDLANDS","pc":"DY7 5EP","ac":"U"},{"n":"WLHC PROJECTCO LIMITED","num":"07052846","sic":"91011","y":"2009","t":"NOTTINGHAM","r":"","pc":"NG8 6PY","ac":"S"},{"n":"YORK MUSEUMS AND ENTERPRISES LIMITED","num":"04466798","sic":"91020","y":"2002","t":"YORK","r":"","pc":"YO30 7DR","ac":"S"},{"n":"YORKSHIRE WILDLIFE SERVICES LIMITED","num":"09922108","sic":"91040","y":"2015","t":"YORK","r":"","pc":"YO24 1GN","ac":"S"}]